{"dependencies":[{"name":"./js\\index.js","dynamic":true},{"name":"./img\\insta.png","dynamic":true},{"name":"./img\\linkedin.png","dynamic":true},{"name":"./img\\gmail.png","dynamic":true},{"name":"./aboutme.html","dynamic":true,"entry":true},{"name":"./works.html","dynamic":true,"entry":true},{"name":"./contacto.html","dynamic":true,"entry":true},{"name":"./index.html","dynamic":true,"entry":true},{"name":"./img\\logo.png","dynamic":true},{"name":"./img\\fotoproyecto4.jpg","dynamic":true},{"name":"./img\\fotoproyecto4.2.jpg","dynamic":true},{"name":"./img\\fotoproyecto4.3.jpg","dynamic":true},{"name":"./img\\flecha.png","dynamic":true}],"generated":{"html":"<!DOCTYPE html>\r\n<html>\r\n<head>\r\n<meta charset=\"ytf-8\">\r\n<meta name=\"viewport\" content=\"width=device-width, initial-scale=1.0\">\r\n<title> Elisa Casto </title>\r\n<script src=\"/js.7df28b89.js\"></script>\r\n</head>\r\n<body>\r\n<header>\r\n<div class=\"header\">\r\n        <div class=\"rshero none\">\r\n                <a href=\"https://www.instagram.com/graphic_elisa/\"><img class=\"instagram\" src=\"/insta.88efa034.png\" alt=\"instagram's icon\"></a>\r\n                <a href=\"https://www.linkedin.com/in/elisa-casto-90769814a/\"><img class=\"linkedin\" src=\"/linkedin.cba1ac69.png\" alt=\"linkedin's icon\"></a>\r\n                <a href=\"mailto:castoelisa8@gmail.com\"><img class=\"gmail\" src=\"/gmail.18006e75.png\" alt=\"gmail's icon\"></a>\r\n        </div>\r\n<div class=\"menu\"> \r\n        <ul>\r\n        <li><a class=\"uno\" href=\"/aboutme.html\">About me</a></li>\r\n        <li><a class=\"active\" href=\"/works.html\">Works</a></li>\r\n        <li><a class=\"tres\" href=\"/contacto.html\">Contact</a></li>\r\n        </ul>\r\n</div>\r\n<a href=\"/index.html\"><img class=\"logoheader\" src=\"/logo.d5171476.png\" alt=\"logo Elisa Casto\"></a>\r\n</div>\r\n</header>\r\n<div class=\"containerproyecto\">\r\n<div class=\"proyectcontainer\">\r\n        <h1 class=\"titulo projects\">Web design’s works</h1>\r\n        <hr class=\"csIntroDivider csIntroDivider-project4\">\r\n        <div class=\"containerwork\">\r\n            <img class=\"imgproyecto center\" src=\"/fotoproyecto4.a80f9cfe.jpg\" alt=\"third project's photo\">\r\n        <div class=\"fichaproyecto\">\r\n            <h3 class=\"latoh3\">Design of recipe web page</h3>\r\n            <p class=\"plight back\">Personal project</p>\r\n            <p class=\"plight back\">2017</p>\r\n        </div>\r\n        </div>\r\n</div>\r\n\r\n<div class=\"proyectcontainer\">\r\n        <div class=\"containerwork\">\r\n            <img class=\"imgproyecto center\" src=\"/fotoproyecto4.2.1b78c893.jpg\" alt=\"third project's photo\">\r\n        <div class=\"fichaproyecto\">\r\n                <h3 class=\"latoh3\">Design of tourist web page</h3>\r\n                <p class=\"plight back\">Personal project</p>\r\n                <p class=\"plight back\">2018</p>\r\n        </div>\r\n        </div>\r\n</div>\r\n\r\n<div class=\"proyectcontainer\">\r\n        <div class=\"containerwork\">\r\n            <img class=\"imgproyecto center\" src=\"/fotoproyecto4.3.10498221.jpg\" alt=\"third project's photo\">\r\n        <div class=\"fichaproyecto\">\r\n            <h3 class=\"latoh3\">Design of “Madrid city tour” web-app</h3>\r\n            <p class=\"plight back\">Personal project</p>\r\n            <p class=\"plight back\">2018</p>\r\n        </div>\r\n        </div>\r\n</div>\r\n\r\n\r\n</div>\r\n<div class=\"backportfolio\">\r\n        <a href=\"/works.html\"><img class=\"flechaback\" src=\"/flecha.8dd67723.png\">\r\n        <div class=\"p back\">Back to works</div></a>\r\n</div>\r\n<footer class=\"cajafooter\">\r\n    <div class=\"footercontainer\">\r\n            <div class=\"textofooter\">\r\n                    <h3 class=\"latoh3\">To collaborate with me<br><strong>contact using the links below</strong></h3>\r\n            </div>\r\n            <div class=\"redessociales\">\r\n                    <a href=\"https://www.instagram.com/graphic_elisa/\"><img class=\"instagram\" src=\"/insta.88efa034.png\" alt=\"instagram's icon\"></a>\r\n                    <a href=\"https://www.linkedin.com/in/elisa-casto-90769814a/\"><img class=\"linkedin\" src=\"/linkedin.cba1ac69.png\" alt=\"linkedin's icon\"></a>\r\n                    <a href=\"#\"><img class=\"gmail\" src=\"/gmail.18006e75.png\" alt=\"gmail's icon\"></a>\r\n            </div>\r\n    </div>\r\n</footer>\r\n<div class=\"copyright\">\r\n        <div>2018 ©Elisa Casto-Graphic and editorial designer|All rights reserved.</div>\r\n</div>\r\n</body>\r\n</html>"},"hash":"b3b0abbe76439dd108310b2269c1e028","cacheData":{}}